CHANGES.txt
LICENSE.txt
README.txt
bootstrap.py
buildout.cfg
setup.py
src/jquery/__init__.py
src/jquery.javascript.egg-info/PKG-INFO
src/jquery.javascript.egg-info/SOURCES.txt
src/jquery.javascript.egg-info/dependency_links.txt
src/jquery.javascript.egg-info/namespace_packages.txt
src/jquery.javascript.egg-info/not-zip-safe
src/jquery.javascript.egg-info/requires.txt
src/jquery.javascript.egg-info/top_level.txt
src/jquery/javascript/License.txt
src/jquery/javascript/__init__.py
src/jquery/javascript/browser.py
src/jquery/javascript/js/jquery-1.1.2.js
src/jquery/javascript/js/jquery.js
src/jquery/javascript/js/jquery.pack.js
src/jquery/javascript/js/json.js
src/jquery/javascript/js/xmlhttp.js
