Metadata-Version: 1.0
Name: jquery.javascript
Version: 1.0.0
Summary: JQuery integration into Zope 3 via Viewlets
Home-page: http://cheeseshop.python.org/pypi/jquery.javascript
Author: Roger Ineichen and the Zope Community
Author-email: zope3-dev@zope.org
License: ZPL 2.1
Keywords: zope3 javascript jquery
Platform: UNKNOWN
Classifier: Development Status :: 4 - Beta
Classifier: Environment :: Web Environment
Classifier: Intended Audience :: Developers
Classifier: License :: OSI Approved :: Zope Public License
Classifier: Programming Language :: Python
Classifier: Natural Language :: English
Classifier: Operating System :: OS Independent
Classifier: Topic :: Internet :: WWW/HTTP
Classifier: Framework :: Zope3
